{
  "id": "xy6-105",
  "name": "M Rayquaza-EX",
  "set": "Roaring Skies",
  "set_id": "xy6",
  "number": "105",
  "rarity": "Rare Ultra",
  "image": "https://images.pokemontcg.io/xy6/105.png",
  "large_image": "https://images.pokemontcg.io/xy6/105_hires.png",
  "printing_type": "Holofoil",
  "supertype": "Pok\u00e9mon",
  "subtypes": [
    "MEGA",
    "EX"
  ],
  "tcgplayer": {
    "holofoil": {
      "low": 111.05,
      "mid": 199.99,
      "high": 350.0,
      "market": 173.67,
      "directLow": 199.98
    },
    "market": 173.67,
    "primary_variant": "holofoil",
    "is_holofoil": true,
    "is_first_edition": false,
    "is_reverse_holo": false
  },
  "tcgplayer_url": "https://prices.pokemontcg.io/tcgplayer/xy6-105",
  "price_charting": {
    "loose": 105.06,
    "new": 145.0,
    "graded": 279.09,
    "graded_variants": {
      "bgs-10": 910.0,
      "box-only": 427.92,
      "cib": 119.96,
      "condition-17": 57.62,
      "condition-18": 420.0,
      "gamestop": 0.0,
      "gamestop-trade": 0.0,
      "loose": 105.06,
      "manual-only": 699.7,
      "new": 145.0
    },
    "bgs_grades": {
      "bgs-10": 910.0
    }
  },
  "pricecharting_url": "https://www.pricecharting.com/game/pokemon-card/958928",
  "cardmarket": {
    "averageSellPrice": 120.39,
    "lowPrice": 16.0,
    "trendPrice": 114.7,
    "germanProLow": 0.0,
    "suggestedPrice": 0.0,
    "reverseHoloSell": 0.0,
    "reverseHoloLow": 0.0,
    "reverseHoloTrend": 70.19,
    "lowPriceExPlus": 45.0,
    "avg1": 90.0,
    "avg7": 140.02,
    "avg30": 87.27,
    "reverseHoloAvg1": 34.99,
    "reverseHoloAvg7": 71.42,
    "reverseHoloAvg30": 36.97,
    "trendPrice_usd": 125.02300000000001,
    "exchangeRate": 1.09,
    "avg1_usd": 98.10000000000001
  },
  "cardmarket_url": "https://prices.pokemontcg.io/cardmarket/xy6-105",
  "arbitrage": {
    "buy_from": "pricecharting",
    "buy_price": 105.06,
    "sell_to": "tcgplayer",
    "sell_price": 173.67,
    "net_sell_price": 147.6195,
    "profit": 41.559499999999986,
    "profit_margin": 39.557871692366255
  }
}